{
  "generated_at": "2026-06-10T14:32:59Z",
  "item_count": 6,
  "period": {
    "end": "2026-06-10T15:00:00Z",
    "start": "2026-06-10T14:00:00Z"
  },
  "report_id": "hourly:2026-06-10T14:00:00Z",
  "sections": [
    {
      "heading": "AI 安全相关",
      "item_ids": [
        "itm_760c1ba446129cb0",
        "itm_8e5f12d79ac963da"
      ],
      "summary": "AI 安全相关 本次共有 2 条内容进入公开数据，详见对应 Markdown 深读稿。"
    },
    {
      "heading": "大模型 Agent 相关",
      "item_ids": [
        "itm_1a7515fa4ecc6350",
        "itm_a78e5b77c7a896b3"
      ],
      "summary": "大模型 Agent 相关 本次共有 2 条内容进入公开数据，详见对应 Markdown 深读稿。"
    },
    {
      "heading": "大模型后训练相关",
      "item_ids": [
        "itm_de731de0ab961aa3",
        "itm_eaedaddebf930f97"
      ],
      "summary": "大模型后训练相关 本次共有 2 条内容进入公开数据，详见对应 Markdown 深读稿。"
    }
  ],
  "summary": "本小时 public data 由 finalize-public-run 机械更新，共收录 6 条内容。",
  "top_item_ids": [
    "itm_760c1ba446129cb0",
    "itm_de731de0ab961aa3",
    "itm_1a7515fa4ecc6350",
    "itm_8e5f12d79ac963da",
    "itm_a78e5b77c7a896b3"
  ],
  "version": 1
}
