{
  "generated_at": "2026-06-08T20:25:50Z",
  "item_count": 1,
  "period": {
    "end": "2026-06-08T21:00:00Z",
    "start": "2026-06-08T20:00:00Z"
  },
  "report_id": "hourly:2026-06-08T20:00:00Z",
  "sections": [
    {
      "heading": "大模型后训练相关",
      "item_ids": [
        "itm_bf61e43c788e1406"
      ],
      "summary": "OpenEnv 把 agentic RL 的环境层收窄为协议、部署和消费接口，给 TRL、Unsloth、TorchForge、SkyRL 等后训练框架提供可复用环境插头。"
    }
  ],
  "summary": "本小时深读 Hugging Face 2026-06-08 OpenEnv 公告，重点分析 Agentic RL 环境协议层、MCP、HF Spaces 部署、harness integration、taskset/external import/auto-validation RFC，以及项目仍处 experimental stage 的边界。",
  "top_item_ids": [
    "itm_bf61e43c788e1406"
  ],
  "version": 1
}
